{
  "Routes": [
    {
      "DownstreamHostAndPorts": [
        {
          "Host": "$HOST_CC",
          "Port": "$PORT_CC"
        }
      ],
      "DownstreamPathTemplate": "/service/timeslotservice/Timeslot/GetTimeslots",
      "DownstreamScheme": "https",
      "UpstreamHttpMethod": [
        "Get",
        "Options"
      ],
      "UpstreamPathTemplate": "/timeslotservice/Timeslot/GetTimeslots"
    },
    {
      "DownstreamHostAndPorts": [
        {
          "Host": "$HOST_CC",
          "Port": "$PORT_CC"
        }
      ],
      "DownstreamPathTemplate": "/service/timeslotservice/Timeslot/ReserveTimeslots",
      "DownstreamScheme": "https",
      "UpstreamHttpMethod": [
        "Post",
        "Options"
      ],
      "UpstreamPathTemplate": "/timeslotservice/Timeslot/ReserveTimeslots"
    },
    {
      "DownstreamHostAndPorts": [
        {
          "Host": "$HOST_CC",
          "Port": "$PORT_CC"
        }
      ],
      "DownstreamPathTemplate": "/service/timeslotservice/Timeslot/DeleteTimeslot",
      "DownstreamScheme": "https",
      "UpstreamHttpMethod": [
        "Post",
        "Options"
      ],
      "UpstreamPathTemplate": "/timeslotservice/Timeslot/DeleteTimeslot"
    },
    {
      "DownstreamHostAndPorts": [
        {
          "Host": "$HOST_CC",
          "Port": "$PORT_CC"
        }
      ],
      "DownstreamPathTemplate": "/service/timeslotservice/api/v2/Timeslot",
      "DownstreamScheme": "https",
      "UpstreamHttpMethod": [
        "Get",
        "Options"
      ],
      "UpstreamPathTemplate": "/timeslotservice/api/v2/Timeslot"
    },
    {
      "DownstreamHostAndPorts": [
        {
          "Host": "$HOST_CC",
          "Port": "$PORT_CC"
        }
      ],
      "DownstreamPathTemplate": "/service/timeslotservice/api/v2/Timeslot/AutoInterval",
      "DownstreamScheme": "https",
      "UpstreamHttpMethod": [
        "Get",
        "Options"
      ],
      "UpstreamPathTemplate": "/timeslotservice/api/v2/Timeslot/AutoInterval"
    },
    {
      "DownstreamHostAndPorts": [
        {
          "Host": "$HOST_CC",
          "Port": "$PORT_CC"
        }
      ],
      "DownstreamPathTemplate": "/service/timeslotservice/api/v2/Timeslot/Change",
      "DownstreamScheme": "https",
      "UpstreamHttpMethod": [
        "Post",
        "Options"
      ],
      "UpstreamPathTemplate": "/timeslotservice/api/v2/Timeslot/Change"
    }
  ]
}